LICENSE
MANIFEST.in
README.rst
setup.cfg
setup.py
exceltojson/__init__.py
exceltojson/console.py
exceltojson/excel2json.py
exceltojson/utils.py
exceltojson.egg-info/PKG-INFO
exceltojson.egg-info/SOURCES.txt
exceltojson.egg-info/dependency_links.txt
exceltojson.egg-info/entry_points.txt
exceltojson.egg-info/requires.txt
exceltojson.egg-info/top_level.txt