Metadata-Version: 1.1
Name: exceltojson
Version: 1.0.1
Summary: transform excel file to json files
Home-page: https://github.com/malongge/exceltojson
Author: malongge thomas
Author-email: 794589200@qq.com
License: MIT
Keywords: transform excel to json files
Platform: UNKNOWN
Classifier: Development Status :: 5 - Production/Stable
Classifier: Intended Audience :: Developers
Classifier: Topic :: Software Development :: Build Tools
Classifier: License :: OSI Approved :: MIT License
Classifier: Programming Language :: Python :: 2
Classifier: Programming Language :: Python :: 2.6
Classifier: Programming Language :: Python :: 2.7
Classifier: Programming Language :: Python :: 3
Classifier: Programming Language :: Python :: 3.3
Classifier: Programming Language :: Python :: 3.4
Classifier: Programming Language :: Python :: 3.5
